chbs/__init__.py
chbs/server.py
chbs-0.2.2.dist-info/LICENSE
chbs-0.2.2.dist-info/METADATA
chbs-0.2.2.dist-info/WHEEL
chbs-0.2.2.dist-info/entry_points.txt
chbs-0.2.2.dist-info/top_level.txt
chbs-0.2.2.dist-info/RECORD
