Metadata-Version: 2.1
Name: chbs
Version: 0.2.2
Summary: UNKNOWN
Home-page: https://github.com/waynew/correcthorsebatterystaple
Author: Wayne Werner
Author-email: wayne@waynewerner.com
License: UNKNOWN
Platform: UNKNOWN
Classifier: License :: OSI Approved :: MIT License
Provides-Extra: build
Requires-Dist: wheel ; extra == 'build'
Provides-Extra: test
Requires-Dist: pytest ; extra == 'test'
